mbstrdecoder/__init__.py
mbstrdecoder/__version__.py
mbstrdecoder/_binary_ext_checker.py
mbstrdecoder/_func.py
mbstrdecoder/_mbstrdecoder.py
mbstrdecoder/py.typed
mbstrdecoder-1.1.3.dist-info/LICENSE
mbstrdecoder-1.1.3.dist-info/METADATA
mbstrdecoder-1.1.3.dist-info/WHEEL
mbstrdecoder-1.1.3.dist-info/top_level.txt
mbstrdecoder-1.1.3.dist-info/RECORD
